AutoMMM/__init__.py
AutoMMM/autoholidays.py
AutoMMM/automodeller.py
AutoMMM/bayes.py
autoMMM-0.1.5.dist-info/METADATA
autoMMM-0.1.5.dist-info/WHEEL
autoMMM-0.1.5.dist-info/top_level.txt
autoMMM-0.1.5.dist-info/RECORD
